conixposter/__init__.py
conixposter/conixposter.py
conixposter-0.0.9.data/scripts/conix-post
conixposter-0.0.9.dist-info/METADATA
conixposter-0.0.9.dist-info/RECORD
conixposter-0.0.9.dist-info/WHEEL
conixposter-0.0.9.dist-info/top_level.txt
